pathlint/__init__.py
pathlint/_version.py
pathlint/autofix.py
pathlint/linter.py
pathlint-0.1.0.dist-info/METADATA
pathlint-0.1.0.dist-info/WHEEL
pathlint-0.1.0.dist-info/entry_points.txt
pathlint-0.1.0.dist-info/licenses/LICENSE.txt
pathlint-0.1.0.dist-info/RECORD
