Metadata-Version: 2.4
Name: pathlint
Version: 0.1.0
Summary: Fast linter to detect os.path usage and encourage pathlib adoption
Project-URL: Repository, https://github.com/pszemraj/pathlint
Project-URL: Issues, https://github.com/pszemraj/pathlint/issues
Project-URL: Changelog, https://github.com/pszemraj/pathlint/releases
Project-URL: Documentation, https://github.com/pszemraj/pathlint#readme
Author-email: Peter Szemraj <peterszemraj+dev@gmail.com>
License: MIT
License-File: LICENSE.txt
Keywords: ast,code-quality,linter,os.path,pathlib,python-linter,static-analysis
Classifier: Development Status :: 4 - Beta
Classifier: Environment :: Console
Classifier: Intended Audience :: Developers
Classifier: License :: OSI Approved :: MIT License
Classifier: Programming Language :: Python :: 3.8
Classifier: Programming Language :: Python :: 3.9
Classifier: Programming Language :: Python :: 3.10
Classifier: Programming Language :: Python :: 3.11
Classifier: Programming Language :: Python :: 3.12
Classifier: Topic :: Software Development :: Quality Assurance
Requires-Python: >=3.8
Provides-Extra: dev
Requires-Dist: mypy>=1.0; extra == 'dev'
Requires-Dist: ruff>=0.1.0; extra == 'dev'
Provides-Extra: test
Requires-Dist: pytest-cov>=4.0; extra == 'test'
Requires-Dist: pytest>=7.0; extra == 'test'
